sopel_sports/__init__.py
sopel_sports/mlb.py
sopel_sports/nfl.py
sopel_sports/nhl.py
sopel_sports-2.3.1.dist-info/licenses/LICENSE
sopel_sports-2.3.1.dist-info/METADATA
sopel_sports-2.3.1.dist-info/WHEEL
sopel_sports-2.3.1.dist-info/entry_points.txt
sopel_sports-2.3.1.dist-info/top_level.txt
sopel_sports-2.3.1.dist-info/RECORD
