Metadata-Version: 2.4
Name: sopel-sports
Version: 2.3.1
Summary: Sopel Sports Module
Author-email: Rusty Bower <rusty@rustybower.com>
Maintainer-email: Rusty Bower <rusty@rustybower.com>
License: MIT
Project-URL: Homepage, https://github.com/RustyBower/sopel-sports
Project-URL: Bug Tracker, https://github.com/RustyBower/sopel-sports/issues
Keywords: sopel,plugin,sports,nfl,nhl,mlb,bot,irc
Platform: Linux x86, x86-64
Classifier: Development Status :: 5 - Production/Stable
Classifier: Intended Audience :: Developers
Classifier: Intended Audience :: System Administrators
Classifier: Operating System :: POSIX :: Linux
Classifier: Programming Language :: Python :: 3.8
Classifier: Programming Language :: Python :: 3.9
Classifier: Programming Language :: Python :: 3.10
Classifier: Programming Language :: Python :: 3.11
Classifier: Programming Language :: Python :: 3.12
Classifier: Topic :: Communications :: Chat :: Internet Relay Chat
Requires-Python: <4,>=3.8
License-File: LICENSE
Requires-Dist: arrow
Requires-Dist: requests
Requires-Dist: sopel>=8
Dynamic: license-file
